odoo10_addon_l10n_br_account_payment_order-10.0.2.0.0.99.dev12-py3.8-nspkg.pth
odoo/addons/l10n_br_account_payment_order/README.rst
odoo/addons/l10n_br_account_payment_order/__init__.py
odoo/addons/l10n_br_account_payment_order/__manifest__.py
odoo/addons/l10n_br_account_payment_order/demo/account_payment_mode_demo.xml
odoo/addons/l10n_br_account_payment_order/demo/account_payment_order_demo.xml
odoo/addons/l10n_br_account_payment_order/i18n/l10n_br_account_payment_order.pot
odoo/addons/l10n_br_account_payment_order/models/__init__.py
odoo/addons/l10n_br_account_payment_order/models/account_move_line.py
odoo/addons/l10n_br_account_payment_order/models/account_payment_line.py
odoo/addons/l10n_br_account_payment_order/models/account_payment_mode.py
odoo/addons/l10n_br_account_payment_order/models/res_partner_bank.py
odoo/addons/l10n_br_account_payment_order/readme/CONFIGURE.rst
odoo/addons/l10n_br_account_payment_order/readme/CONTRIBUTORS.rst
odoo/addons/l10n_br_account_payment_order/readme/CREDITS.rst
odoo/addons/l10n_br_account_payment_order/readme/DESCRIPTION.rst
odoo/addons/l10n_br_account_payment_order/readme/HISTORY.rst
odoo/addons/l10n_br_account_payment_order/readme/INSTALL.rst
odoo/addons/l10n_br_account_payment_order/readme/ROADMAP.rst
odoo/addons/l10n_br_account_payment_order/readme/USAGE.rst
odoo/addons/l10n_br_account_payment_order/static/description/icon.png
odoo/addons/l10n_br_account_payment_order/static/description/index.html
odoo/addons/l10n_br_account_payment_order/tests/__init__.py
odoo/addons/l10n_br_account_payment_order/tests/test_payment_order.py
odoo/addons/l10n_br_account_payment_order/views/account_due_list.xml
odoo/addons/l10n_br_account_payment_order/views/account_payment_line.xml
odoo/addons/l10n_br_account_payment_order/views/account_payment_mode.xml
odoo/addons/l10n_br_account_payment_order/views/account_payment_order_menu_views.xml
odoo10_addon_l10n_br_account_payment_order-10.0.2.0.0.99.dev12.dist-info/METADATA
odoo10_addon_l10n_br_account_payment_order-10.0.2.0.0.99.dev12.dist-info/WHEEL
odoo10_addon_l10n_br_account_payment_order-10.0.2.0.0.99.dev12.dist-info/namespace_packages.txt
odoo10_addon_l10n_br_account_payment_order-10.0.2.0.0.99.dev12.dist-info/top_level.txt
odoo10_addon_l10n_br_account_payment_order-10.0.2.0.0.99.dev12.dist-info/RECORD
