Metadata-Version: 2.1
Name: odoo10-addon-l10n-br-account-payment-order
Version: 10.0.2.0.0.99.dev12
Summary: Brazilian Payment Order
Home-page: https://github.com/OCA/l10n-brazil
Author: KMEE, Odoo Community Association (OCA)
Author-email: support@odoo-community.org
License: AGPL-3
Platform: UNKNOWN
Classifier: Programming Language :: Python
Classifier: Framework :: Odoo
Classifier: Framework :: Odoo :: 10.0
Classifier: License :: OSI Approved :: GNU Affero General Public License v3
Requires-Python: ~=2.7
Requires-Dist: odoo10-addon-account-due-list
Requires-Dist: odoo10-addon-account-payment-order
Requires-Dist: odoo10-addon-l10n-br-account
Requires-Dist: odoo <10.1dev,>=10.0
